LICENSE
hyperion/__init__.py
hyperion/client.py
hyperion/const.py
hyperion/py.typed
hyperhdr_py_redux-0.7.8.dist-info/LICENSE
hyperhdr_py_redux-0.7.8.dist-info/METADATA
hyperhdr_py_redux-0.7.8.dist-info/WHEEL
hyperhdr_py_redux-0.7.8.dist-info/RECORD
