Metadata-Version: 2.1
Name: hyperhdr-py-redux
Version: 0.7.8
Summary: Hyperion Ambient Lighting Python Package
Home-page: https://github.com/andrew-kennedy/hyperion-py
License: MIT
Keywords: hyperion
Author: Andrew Kennedy
Author-email: andrewk36@gmail.com
Requires-Python: >=3.8,<4.0
Classifier: Intended Audience :: Developers
Classifier: License :: OSI Approved :: MIT License
Classifier: Operating System :: OS Independent
Classifier: Programming Language :: Python :: 3
Classifier: Programming Language :: Python :: 3.8
Classifier: Programming Language :: Python :: 3.9
Classifier: Programming Language :: Python :: 3.10
Classifier: Programming Language :: Python :: 3.11
Classifier: Programming Language :: Python :: 3.12
Classifier: Topic :: Home Automation
Project-URL: Repository, https://github.com/andrew-kennedy/hyperion-py
